setup.py
ray_py_tools/__init__.py
ray_py_tools.egg-info/PKG-INFO
ray_py_tools.egg-info/SOURCES.txt
ray_py_tools.egg-info/dependency_links.txt
ray_py_tools.egg-info/requires.txt
ray_py_tools.egg-info/top_level.txt
ray_py_tools/utils/LoggerUtil.py
ray_py_tools/utils/RequestUtil.py
ray_py_tools/utils/StringUtil.py
ray_py_tools/utils/__init__.py